dckit/__init__.py
dckit/__main__.py
dckit/_version.py
dckit/_version_save.py
dckit/dlg_icheck.py
dckit/dlg_icheck.ui
dckit/dlg_join.ui
dckit/dlg_log.ui
dckit/dlg_repack.ui
dckit/history.py
dckit/main.py
dckit/main.ui
dckit/message_box.py
dckit/meta_tool.py
dckit/preferences.py
dckit/preferences.ui
dckit/update.py
dckit/wait_cursor.py
dckit/img/icon.png
dckit/img/splash.png
dckit-0.17.7.dist-info/LICENSE
dckit-0.17.7.dist-info/METADATA
dckit-0.17.7.dist-info/WHEEL
dckit-0.17.7.dist-info/entry_points.txt
dckit-0.17.7.dist-info/top_level.txt
dckit-0.17.7.dist-info/RECORD
