Metadata-Version: 2.1
Name: dckit
Version: 0.17.7
Summary: Graphical toolkit for RT-DC data management
Home-page: https://github.com/DC-analysis/DCKit
Author: Paul Müller
Author-email: dev@craban.de
License: GPL-3.0-or-later
Keywords: RT-DC,deformability,cytometry,zellmechanik
Platform: ALL
Classifier: Operating System :: OS Independent
Classifier: Programming Language :: Python :: 3
Classifier: Intended Audience :: Science/Research
Requires-Python: >=3.10, <4
License-File: LICENSE
Requires-Dist: dclab[tdms]>=0.67.0
Requires-Dist: h5py>=3.9.0
Requires-Dist: imageio[ffmpeg]
Requires-Dist: nptdms>=0.27.0
Requires-Dist: numpy>=1.21
Requires-Dist: pyqt5
